supabase_models/__init__.py
supabase_models/__main__.py
supabase_models/cli.py
supabase_models/config.py
supabase_models/default.jinja2
supabase_models/generator.py
supabase_models/py.typed
supabase_models/common/__init__.py
supabase_models/common/schemas.py
supabase_models/common/utils.py
supabase_models/components/__init__.py
supabase_models/components/constraint_parser.py
supabase_models/components/database_manager.py
supabase_models/components/model_extractor.py
supabase_models/components/output_manager.py
supabase_models-0.0.3.dist-info/METADATA
supabase_models-0.0.3.dist-info/WHEEL
supabase_models-0.0.3.dist-info/entry_points.txt
supabase_models-0.0.3.dist-info/licenses/LICENSE
supabase_models-0.0.3.dist-info/RECORD
