Metadata-Version: 2.4
Name: supabase-models
Version: 0.0.3
Summary: Generate type-safe Pydantic models that simplify working with supabase-py
Project-URL: Homepage, https://github.com/martin-foka/supabase-models
Project-URL: Repository, https://github.com/martin-foka/supabase-models
Project-URL: Issues, https://github.com/martin-foka/supabase-models/issues
Author: martin-foka
License: MIT
License-File: LICENSE
Keywords: codegen,database,generator,models,postgresql,pydantic,schema,sqlalchemy,supabase,supabase-py
Classifier: Development Status :: 4 - Beta
Classifier: Intended Audience :: Developers
Classifier: License :: OSI Approved :: MIT License
Classifier: Operating System :: OS Independent
Classifier: Programming Language :: Python :: 3
Classifier: Programming Language :: Python :: 3.10
Classifier: Programming Language :: Python :: 3.11
Classifier: Programming Language :: Python :: 3.12
Classifier: Programming Language :: Python :: 3.13
Classifier: Topic :: Database
Classifier: Topic :: Software Development :: Code Generators
Classifier: Typing :: Typed
Requires-Python: >=3.10
Requires-Dist: inflect>=7.0.0
Requires-Dist: jinja2>=3.1.0
Requires-Dist: psycopg2-binary>=2.9.0
Requires-Dist: pydantic>=2.0.0
Requires-Dist: sqlalchemy>=2.0.0
